ai_llama_module/__init__.py
ai_llama_module/ai.py
ai_llama_module-0.1.6.dist-info/METADATA
ai_llama_module-0.1.6.dist-info/WHEEL
ai_llama_module-0.1.6.dist-info/top_level.txt
ai_llama_module-0.1.6.dist-info/RECORD
