Metadata-Version: 2.4
Name: ai_llama_module
Version: 0.1.6
Summary: Simple and lightweight Python wrapper for Llama AI API
Author-email: Isaac Gallienne <100033398@mvla.net>
License-Expression: MIT AND Apache-2.0
Requires-Python: >=3.9
Requires-Dist: requests>=2.28.0
Requires-Dist: python-dotenv>=0.21.0
